runit_server/Request.py
runit_server/__init__.py
runit_server/app.py
runit_server/auth.py
runit_server/aws.py
runit_server/azure.py
runit_server/cli.py
runit_server/constants.py
runit_server/core.py
runit_server/dockerize.py
runit_server/exceptions.py
runit_server/favicon.ico
runit_server/gcloud.py
runit_server/kubernetes-1.py
runit_server/kubernetes-2.py
runit_server/test.py
runit_server/common/__init__.py
runit_server/common/fast_api.py
runit_server/common/security.py
runit_server/common/utils.py
runit_server/models/__init__.py
runit_server/models/admin.py
runit_server/models/collection.py
runit_server/models/data.py
runit_server/models/database.py
runit_server/models/function.py
runit_server/models/permission.py
runit_server/models/project.py
runit_server/models/role.py
runit_server/models/user.py
runit_server/modules/__init__.py
runit_server/modules/account.py
runit_server/routers/__init__.py
runit_server/routers/account.py
runit_server/routers/admin.py
runit_server/routers/database.py
runit_server/routers/functions.py
runit_server/routers/github.py
runit_server/routers/project.py
runit_server/routers/public.py
runit_server/routers/setup.py
runit_server/routers/api/__init__.py
runit_server/routers/api/account.py
runit_server/routers/api/base.py
runit_server/routers/api/database.py
runit_server/routers/api/project.py
runit_server/routers/api/public.py
runit_server/static/css/all.min.css
runit_server/static/css/bootstrap.min.css
runit_server/static/css/bootstrap.min.css.map
runit_server/static/css/styles.css
runit_server/static/images/dark-terminal.svg
runit_server/static/images/loading.gif
runit_server/static/images/terminal.svg
runit_server/static/images/logos/html5.svg
runit_server/static/images/logos/nodejs.png
runit_server/static/images/logos/nodejs.svg
runit_server/static/images/logos/php.svg
runit_server/static/images/logos/python.png
runit_server/static/images/logos/python.svg
runit_server/static/images/logos/python1.svg
runit_server-0.4.2.dist-info/LICENSE
runit_server-0.4.2.dist-info/METADATA
runit_server-0.4.2.dist-info/WHEEL
runit_server-0.4.2.dist-info/entry_points.txt
runit_server-0.4.2.dist-info/top_level.txt
runit_server-0.4.2.dist-info/RECORD
