Metadata-Version: 2.1
Name: runit-server
Version: 0.4.2
Summary: Backend for python-runit
Author: Amos Amissah
Author-email: theonlyamos@gmail.com
Project-URL: Source, https://github.com/theonlyamos/runit-server/
Project-URL: Tracker, https://github.com/theonlyamos/runit-server/issues
Keywords: python3 runit server backend developer serverless architecture docker
Classifier: Development Status :: 3 - Alpha
Classifier: Intended Audience :: Developers
Classifier: Topic :: Software Development :: Build Tools
Classifier: License :: OSI Approved :: MIT License
Classifier: Programming Language :: Python :: 3
Classifier: Programming Language :: Python :: 3.6
Classifier: Programming Language :: Python :: 3.7
Classifier: Programming Language :: Python :: 3.8
Classifier: Programming Language :: Python :: 3.9
Classifier: Programming Language :: Python :: 3.10
Classifier: Programming Language :: Python :: 3.11
Classifier: Programming Language :: Python :: 3.12
License-File: LICENSE
Requires-Dist: requests
Requires-Dist: python-dotenv
Requires-Dist: runit-cli
Requires-Dist: odbms
Requires-Dist: fastapi
Requires-Dist: python-multipart
Requires-Dist: python-jose[cryptography]
Requires-Dist: passlib
Requires-Dist: docker
Requires-Dist: aiofiles
Requires-Dist: pydantic
Requires-Dist: pydantic[email]
Requires-Dist: jinja2
Requires-Dist: PyGithub
Requires-Dist: itsdangerous
